run_across_america/__init__.py
run_across_america/cli.py
run_across_america/client.py
run_across_america/models.py
run_across_america-0.1.0.dist-info/entry_points.txt
run_across_america-0.1.0.dist-info/LICENSE
run_across_america-0.1.0.dist-info/WHEEL
run_across_america-0.1.0.dist-info/METADATA
run_across_america-0.1.0.dist-info/RECORD
