Metadata-Version: 2.1
Name: run-across-america
Version: 0.1.0
Summary: Run Across America analysis tools
Home-page: https://github.com/minormending/run-across-america
License: MIT
Keywords: run_across_america,run,5k
Author: Kevin Ramdath
Author-email: krpent@gmail.com
Requires-Python: >=3.7,<4.0
Classifier: License :: OSI Approved :: MIT License
Classifier: Programming Language :: Python :: 3
Classifier: Programming Language :: Python :: 3.10
Classifier: Programming Language :: Python :: 3.7
Classifier: Programming Language :: Python :: 3.8
Classifier: Programming Language :: Python :: 3.9
Requires-Dist: requests (>=2.28.1,<3.0.0)
Project-URL: Repository, https://github.com/minormending/run-across-america
